{
  "last_run": "2026-04-10T21:07:12Z",
  "prs": {
    "19476": {
      "status": "merged_or_closed",
      "note": "Not found in current open PR list. Likely merged or closed."
    },
    "19472": {
      "status": "t_gro_active_development_with_fix",
      "last_shepherd_comment": "2026-04-10T21:07:12Z",
      "note": "T-Gro fixed the underlying bug (IlxGen.fs + FS3885 diagnostic). All 48/48 CI pass. Shepherd withdrew close recommendation. PR is now a compiler fix PR, beyond Shepherd scope. Awaiting maintainer review."
    },
    "19471": {
      "status": "skipped_title_mismatch",
      "note": "Title 'Fix #12386...' does not start with 'Add regression test:'. Skipped per eligibility rules."
    },
    "19468": {
      "status": "category_c_clean",
      "note": "46/46 CI pass. All 3 review threads resolved. No new human comments. Category C - healthy."
    }
  }
}
