{
  "sign": [
    {
      "certificate": "Microsoft",
      "strongName": "StrongName",
      "values": [
        "bin\\FSharp.Core\\*\\*\\FSharp.Core.dll",
        "bin\\FSharp.Core\\*\\*\\*\\FSharp.Core.resources.dll",
        "bin\\FSharp.Build\\*\\*\\FSharp.Build.dll",
        "bin\\FSharp.Build\\*\\*\\*\\FSharp.Build.resources.dll",
        "bin\\FSharp.Compiler.Private\\*\\*\\FSharp.Compiler.Private.dll",
        "bin\\FSharp.Compiler.Private\\*\\*\\*\\FSharp.Compiler.Private.resources.dll",
        "bin\\FSharp.Compiler.Server.Shared\\*\\*\\FSharp.Compiler.Server.Shared.dll",
        "bin\\FSharp.Compiler.Interactive.Settings\\*\\*\\FSharp.Compiler.Interactive.Settings.dll",
        "bin\\FSharp.Compiler.Interactive.Settings\\*\\*\\*\\FSharp.Compiler.Interactive.Settings.resources.dll",
        "bin\\fsc\\*\\*\\fsc.exe",
        "bin\\fsi\\*\\*\\fsi.exe",
        "bin\\fsiAnyCpu\\*\\*\\fsiAnyCpu.exe",
        "bin\\FSharp.VS.FSI\\*\\*\\FSharp.VS.FSI.dll",
        "bin\\FSharp.VS.FSI\\*\\*\\*\\FSharp.VS.FSI.resources.dll",
        "bin\\FSharp.LanguageService.Base\\*\\*\\FSharp.LanguageService.Base.dll",
        "bin\\FSharp.LanguageService.Base\\*\\*\\*\\FSharp.LanguageService.Base.resources.dll",
        "bin\\FSharp.LanguageService\\*\\*\\FSharp.LanguageService.dll",
        "bin\\FSharp.LanguageService\\*\\*\\*\\FSharp.LanguageService.resources.dll",
        "bin\\FSharp.UIResources\\*\\*\\FSharp.UIResources.dll",
        "bin\\FSharp.UIResources\\*\\*\\*\\FSharp.UIResources.resources.dll",
        "bin\\FSharp.Editor\\*\\*\\FSharp.Editor.dll",
        "bin\\FSharp.Editor\\*\\*\\*\\FSharp.Editor.resources.dll",
        "bin\\FSharp.PatternMatcher\\*\\*\\FSharp.PatternMatcher.dll",
        "bin\\FSharp.PropertiesPages\\*\\*\\FSharp.ProjectSystem.PropertyPages.dll",
        "bin\\FSharp.PropertiesPages\\*\\*\\*\\FSharp.ProjectSystem.PropertyPages.resources.dll",
        "bin\\ProjectSystem\\*\\*\\FSharp.ProjectSystem.FSharp.dll",
        "bin\\ProjectSystem\\*\\*\\*\\FSharp.ProjectSystem.FSharp.resources.dll",
        "bin\\ProjectSystem.Base\\*\\*\\FSharp.ProjectSystem.Base.dll",
        "bin\\ProjectSystem.Base\\*\\*\\*\\FSharp.ProjectSystem.Base.resources.dll"
      ]
    },
    {
      "certificate": "VsixSHA2",
      "strongName": null,
      "values": [
        "bin\\VisualFSharpFull\\*\\*\\VisualFSharpFull.vsix",
        "bin\\VisualFSharpTemplates\\*\\*\\VisualFSharpTemplate.vsix",
        "VSSetup\\*\\Insertion\\Microsoft.FSharp.Dependencies.vsix",
        "VSSetup\\*\\Insertion\\Microsoft.FSharp.VSIX.Full.Resources.*.vsix"
      ]
    },
    {
      "certificate": "NuGet",
      "strongName": null,
      "values": [
        "packages\\*\\*.nupkg"
      ]
    }
  ],
  "exclude": [
    "e_sqlite3.dll",
    "FSharp.Core.UnitTests.dll",
    "FSharp.Data.TypeProviders.dll",
    "Microsoft.Build.dll",
    "Microsoft.Build.Framework.dll",
    "Microsoft.Build.Tasks.Core.dll",
    "Microsoft.Build.Utilities.Core.dll",
    "Newtonsoft.Json.dll",
    "System.Collections.Immutable.dll",
    "System.Reflection.Metadata.dll",
    "System.ValueTuple.4.4.0.nupkg",
    "System.ValueTuple.dll"
  ]
}
